odoo/addons/country_fr/README.rst
odoo/addons/country_fr/__init__.py
odoo/addons/country_fr/__manifest__.py
odoo/addons/country_fr/partner.xml
odoo/addons/country_fr/i18n/country_fr.pot
odoo/addons/country_fr/readme/CONFIGURE.md
odoo/addons/country_fr/readme/CONTRIBUTORS.md
odoo/addons/country_fr/readme/DESCRIPTION.md
odoo/addons/country_fr/static/description/icon.png
odoo/addons/country_fr/static/description/index.html
odoo_addon_country_fr-18.0.1.0.0.2.dist-info/METADATA
odoo_addon_country_fr-18.0.1.0.0.2.dist-info/WHEEL
odoo_addon_country_fr-18.0.1.0.0.2.dist-info/top_level.txt
odoo_addon_country_fr-18.0.1.0.0.2.dist-info/RECORD
